gguf_cli/__init__.py
gguf_cli/__main__.py
gguf_cli-0.0.1.dist-info/LICENSE
gguf_cli-0.0.1.dist-info/WHEEL
gguf_cli-0.0.1.dist-info/METADATA
gguf_cli-0.0.1.dist-info/RECORD
