Metadata-Version: 2.1
Name: gguf-cli
Version: 0.0.1
Summary: CLI chatbot
Author-email: gguf <info@gguf.us>
Classifier: License :: OSI Approved :: MIT License
